mylescgthomaspy/__init__.py
mylescgthomaspy/data.py
mylescgthomaspy/eda.py
mylescgthomaspy/etl.py
mylescgthomaspy/helpers.py
mylescgthomaspy-0.0.4.dist-info/METADATA
mylescgthomaspy-0.0.4.dist-info/WHEEL
mylescgthomaspy-0.0.4.dist-info/top_level.txt
mylescgthomaspy-0.0.4.dist-info/RECORD
